odoo/addons/pos_membership_extension/README.rst
odoo/addons/pos_membership_extension/__init__.py
odoo/addons/pos_membership_extension/__manifest__.py
odoo/addons/pos_membership_extension/demo/product_product.xml
odoo/addons/pos_membership_extension/i18n/fr.po
odoo/addons/pos_membership_extension/i18n/it.po
odoo/addons/pos_membership_extension/i18n/pos_membership_extension.pot
odoo/addons/pos_membership_extension/models/__init__.py
odoo/addons/pos_membership_extension/models/pos_session.py
odoo/addons/pos_membership_extension/models/product_product.py
odoo/addons/pos_membership_extension/models/product_template.py
odoo/addons/pos_membership_extension/readme/CONFIGURE.rst
odoo/addons/pos_membership_extension/readme/CONTRIBUTORS.rst
odoo/addons/pos_membership_extension/readme/CREDITS.rst
odoo/addons/pos_membership_extension/readme/DESCRIPTION.rst
odoo/addons/pos_membership_extension/readme/ROADMAP.rst
odoo/addons/pos_membership_extension/readme/USAGE.rst
odoo/addons/pos_membership_extension/static/description/icon.png
odoo/addons/pos_membership_extension/static/description/index.html
odoo/addons/pos_membership_extension/static/description/point_of_sale_popup_error.png
odoo/addons/pos_membership_extension/static/description/point_of_sale_popup_product_info.png
odoo/addons/pos_membership_extension/static/description/point_of_sale_product_item.png
odoo/addons/pos_membership_extension/static/description/point_of_sale_switch_partner_popup.png
odoo/addons/pos_membership_extension/static/description/product_form.png
odoo/addons/pos_membership_extension/static/src/css/pos.css
odoo/addons/pos_membership_extension/static/src/js/ProductItem.js
odoo/addons/pos_membership_extension/static/src/js/ProductScreen.js
odoo/addons/pos_membership_extension/static/src/js/models.js
odoo/addons/pos_membership_extension/static/src/xml/ProductInfoPopup.xml
odoo/addons/pos_membership_extension/static/src/xml/ProductItem.xml
odoo/addons/pos_membership_extension/views/view_product_template.xml
odoo_addon_pos_membership_extension-16.0.1.0.1.dist-info/METADATA
odoo_addon_pos_membership_extension-16.0.1.0.1.dist-info/WHEEL
odoo_addon_pos_membership_extension-16.0.1.0.1.dist-info/top_level.txt
odoo_addon_pos_membership_extension-16.0.1.0.1.dist-info/RECORD
