Metadata-Version: 2.1
Name: odoo-addon-pos_membership_extension
Version: 16.0.1.0.1
Summary: Prevent to sale product in the point of sale to customer that don't belong to membership categories
Home-page: https://github.com/OCA/pos
Author: GRAP,Odoo Community Association (OCA)
Author-email: support@odoo-community.org
License: AGPL-3
Classifier: Programming Language :: Python
Classifier: Framework :: Odoo
Classifier: Framework :: Odoo :: 16.0
Classifier: License :: OSI Approved :: GNU Affero General Public License v3
Requires-Python: >=3.10
Requires-Dist: odoo-addon-membership-extension <16.1dev,>=16.0dev
Requires-Dist: odoo <16.1dev,>=16.0a
